pnutpy/__init__.py
pnutpy/api.py
pnutpy/consts.py
pnutpy/cursor.py
pnutpy/errors.py
pnutpy/models.py
pnutpy/utils.py
pnutpy-0.5.4.dist-info/licenses/LICENSE
pnutpy-0.5.4.dist-info/METADATA
pnutpy-0.5.4.dist-info/WHEEL
pnutpy-0.5.4.dist-info/top_level.txt
pnutpy-0.5.4.dist-info/zip-safe
pnutpy-0.5.4.dist-info/RECORD
