Metadata-Version: 2.4
Name: pnutpy
Version: 0.5.4
Summary: pnut.io API library for python
Author-email: "33MHz, pnut.io" <support@pnut.io>, Morgan McMillian <morgan@mcmillian.dev>
License-Expression: MIT
Project-URL: Homepage, https://github.com/pnut-api/PNUTpy
Keywords: pnut.io,api,library
Classifier: Programming Language :: Python :: 3
Classifier: Operating System :: OS Independent
Requires-Python: >=3.10
License-File: LICENSE
Requires-Dist: python-dateutil>=2.9
Requires-Dist: requests>=2.32.5
Dynamic: license-file
